MANIFEST.in
README.txt
setup.cfg
setup.py
docs/HISTORY.txt
docs/INSTALL.txt
docs/LICENSE.GPL
docs/LICENSE.txt
sc/__init__.py
sc.psc.policy.egg-info/PKG-INFO
sc.psc.policy.egg-info/SOURCES.txt
sc.psc.policy.egg-info/dependency_links.txt
sc.psc.policy.egg-info/entry_points.txt
sc.psc.policy.egg-info/namespace_packages.txt
sc.psc.policy.egg-info/not-zip-safe
sc.psc.policy.egg-info/requires.txt
sc.psc.policy.egg-info/top_level.txt
sc/psc/__init__.py
sc/psc/policy/README.txt
sc/psc/policy/__init__.py
sc/psc/policy/config.py
sc/psc/policy/configure.zcml
sc/psc/policy/dependencies.zcml
sc/psc/policy/patches.py
sc/psc/policy/quickinstaller.py
sc/psc/policy/setuphandlers.py
sc/psc/policy/tests.py
sc/psc/policy/version.txt
sc/psc/policy/browser/__init__.py
sc/psc/policy/browser/configure.zcml
sc/psc/policy/docs/__init__.py
sc/psc/policy/docs/browser.txt
sc/psc/policy/locales/manual.pot
sc/psc/policy/locales/rebuildAll.sh
sc/psc/policy/locales/sc.psc.policy.pot
sc/psc/policy/locales/pt_BR/LC_MESSAGES/sc.psc.policy.mo
sc/psc/policy/locales/pt_BR/LC_MESSAGES/sc.psc.policy.po
sc/psc/policy/profiles/default/import_steps.xml
sc/psc/policy/profiles/default/metadata.xml
sc/psc/policy/profiles/default/sc.psc.policy.txt
sc/psc/policy/profiles/uninstall/sc.psc.policy.txt
sc/psc/policy/upgrades/__init__.py
sc/psc/policy/upgrades/configure.zcml
sc/psc/policy/upgrades/to01.py