Metadata-Version: 1.0
Name: sc.psc.policy
Version: 0.6
Summary: A site policy intended to deploy a package repository like                    PyPi or plone.org/downloads, using Plone Software Center
Home-page: https://bitbucket.org/simplesconsultoria/sc.psc.policy
Author: Simples Consultoria
Author-email: products@simplesconsultoria.com.br
License: GPL
Keywords: psc plone package catalog
Platform: UNKNOWN
Classifier: Framework :: Plone
Classifier: Framework :: Zope2
Classifier: Framework :: Zope3
Classifier: Programming Language :: Python
Classifier: Topic :: Software Development :: Libraries :: Python Modules
